setup.py
genshicolumntemplate/__init__.py
genshicolumntemplate.egg-info/PKG-INFO
genshicolumntemplate.egg-info/SOURCES.txt
genshicolumntemplate.egg-info/dependency_links.txt
genshicolumntemplate.egg-info/entry_points.txt
genshicolumntemplate.egg-info/not-zip-safe
genshicolumntemplate.egg-info/requires.txt
genshicolumntemplate.egg-info/top_level.txt
