Metadata-Version: 1.0
Name: genshicolumntemplate
Version: 0.2
Summary: Adds a 3 column layout to the genshi quickstart template for Turbogears.
Home-page: http://lwright.blogspot.com/
Author: Linden Wright
Author-email: linden.wright@gmail.com
License: MIT
Keywords: python.templating.engines
Platform: UNKNOWN
Classifier: Development Status :: 3 - Alpha
Classifier: Operating System :: OS Independent
Classifier: Programming Language :: Python
Classifier: Topic :: Software Development :: Libraries :: Python Modules
Classifier: Framework :: TurboGears
